scrapyd_heroku/__init__.py
scrapyd_heroku/__version__.py
scrapyd_heroku/app.py
scrapyd_heroku-0.2.2.dist-info/LICENSE
scrapyd_heroku-0.2.2.dist-info/METADATA
scrapyd_heroku-0.2.2.dist-info/WHEEL
scrapyd_heroku-0.2.2.dist-info/entry_points.txt
scrapyd_heroku-0.2.2.dist-info/top_level.txt
scrapyd_heroku-0.2.2.dist-info/RECORD
