Metadata-Version: 2.1
Name: scrapyd-heroku
Version: 0.2.2
Summary: Wrapper for running Scrapyd in Heroku or locally as a service
Home-page: https://github.com/jxltom/scrapyd-heroku
Author: jxltom
Author-email: jxltom@gmail.com
License: MIT
Platform: UNKNOWN
Classifier: License :: OSI Approved :: MIT License
Classifier: Programming Language :: Python
Classifier: Programming Language :: Python :: 3
Classifier: Programming Language :: Python :: 3.6
Classifier: Programming Language :: Python :: Implementation :: CPython
Classifier: Programming Language :: Python :: Implementation :: PyPy
Requires-Python: >=3.6.0
Requires-Dist: scrapyd
